LICENSE
MANIFEST.in
README.txt
setup.py
OASYS1_CRYSTALPY.egg-info/PKG-INFO
OASYS1_CRYSTALPY.egg-info/SOURCES.txt
OASYS1_CRYSTALPY.egg-info/dependency_links.txt
OASYS1_CRYSTALPY.egg-info/entry_points.txt
OASYS1_CRYSTALPY.egg-info/namespace_packages.txt
OASYS1_CRYSTALPY.egg-info/not-zip-safe
OASYS1_CRYSTALPY.egg-info/requires.txt
OASYS1_CRYSTALPY.egg-info/top_level.txt
orangecontrib/__init__.py
orangecontrib/crystalpy/__init__.py
orangecontrib/crystalpy/scripts/create_widget.py
orangecontrib/crystalpy/tests/OasysCrystalTests.py
orangecontrib/crystalpy/tests/util/PhotonBunchTest.py
orangecontrib/crystalpy/tests/util/PolarizedPhotonTest.py
orangecontrib/crystalpy/util/MailingBox.py
orangecontrib/crystalpy/util/__init__.py
orangecontrib/crystalpy/widgets/__init__.py
orangecontrib/crystalpy/widgets/elements/Alignment.py
orangecontrib/crystalpy/widgets/elements/BendingMagnet.py
orangecontrib/crystalpy/widgets/elements/Crystal.py
orangecontrib/crystalpy/widgets/elements/CrystalCalculator.py
orangecontrib/crystalpy/widgets/elements/CrystalViewer.py
orangecontrib/crystalpy/widgets/elements/IdealLinearPolarizer.py
orangecontrib/crystalpy/widgets/elements/IdealPhaseRetarder.py
orangecontrib/crystalpy/widgets/elements/OWCrystalpy.py
orangecontrib/crystalpy/widgets/elements/PhotonSource.py
orangecontrib/crystalpy/widgets/elements/PhotonViewer.py
orangecontrib/crystalpy/widgets/elements/ShadowConverter.py
orangecontrib/crystalpy/widgets/elements/__init__.py
orangecontrib/crystalpy/widgets/elements/icons/Alignment.png
orangecontrib/crystalpy/widgets/elements/icons/BendingMagnet.png
orangecontrib/crystalpy/widgets/elements/icons/Crystal.png
orangecontrib/crystalpy/widgets/elements/icons/CrystalCalculator.png
orangecontrib/crystalpy/widgets/elements/icons/CrystalDiffraction.png
orangecontrib/crystalpy/widgets/elements/icons/CrystalViewer.png
orangecontrib/crystalpy/widgets/elements/icons/IdealLinearPolarizer.png
orangecontrib/crystalpy/widgets/elements/icons/IdealPhaseRetarder.png
orangecontrib/crystalpy/widgets/elements/icons/LightBulb.png
orangecontrib/crystalpy/widgets/elements/icons/PhotonViewer.png
orangecontrib/crystalpy/widgets/elements/icons/converter.png
orangecontrib/crystalpy/widgets/elements/icons/xoppy_xcrystal.png